{"raw_detected_boxes": [[], [], [], [], [{"x2": 382.0, "y1": 103.0, "x1": 100.0, "y2": 306.0}], [], [], [], []], "raw_pdffigures_output": {"regionless-captions": [], "figures": [{"figType": "Figure", "name": "3", "captionBoundary": {"x2": 519.76318359375, "y1": 235.4211883544922, "x1": 303.0052795410156, "y2": 255.53436279296875}, "imageText": ["CKM", "391", "Time", "and", "time", "again", "he", "would", "stare", "at", "the", "ground,", "hand", "on", "hip,", "if", "he", "thought", "he", "had", "received", "a", "bad", "call,", "and", "then", "swallow", "his", "anger", "and", "play", "tennis.", "AD9", "3205", "He", "tried", "to", "disguise", "the", "anxiety", "he", "felt", "when", "he", "found", "the", "comms", "system", "down,", "but", "Tammuz", "was", "nearly", "hysterical", "by", "this", "stage.", "AMA", "349", "We", "will", "halt", "the", "reduction", "in", "NHS", "services", "for", "long-term", "care", "and", "community", "health", "services", "which", "support", "elderly", "and", "disabled", "patients", "at", "home.", "ADK", "634", "Catch", "their", "interest", "and", "spark", "their", "enthu-", "siasm", "so", "that", "they", "begin", "to", "see", "the", "product\u2019s", "potential.", "K2W", "1771", "The", "committee", "heard", "today", "that", "gangs", "regu-", "larly", "hurled", "abusive", "comments", "at", "local", "people,", "making", "an", "unacceptable", "level", "of", "noise", "and", "leaving", "litter", "behind", "them."], "regionBoundary": {"x2": 512.0, "y1": 70.67999267578125, "x1": 303.0, "y2": 223.67999267578125}, "caption": "Figure 3: Sentences tagged by the system (metaphors in bold)", "page": 5}, {"figType": "Figure", "name": "2", "captionBoundary": {"x2": 275.0447998046875, "y1": 372.1326599121094, "x1": 85.87529754638672, "y2": 378.70257568359375}, "imageText": ["Source", "Cluster:", "sparkle", "glow", "widen", "\ufb02ash", "\ufb02are", "gleam", "darken", "narrow", "\ufb02icker", "shine", "blaze", "bulge", "Source", "Cluster:", "gulp", "drain", "stir", "empty", "pour", "sip", "spill", "swal-", "low", "drink", "pollute", "seep", "\ufb02ow", "drip", "purify", "ooze", "pump", "bub-", "ble", "splash", "ripple", "simmer", "boil", "tread", "Source", "Cluster:", "polish", "clean", "scrape", "scrub", "soak", "Source", "Cluster:", "kick", "hurl", "push", "\ufb02ing", "throw", "pull", "drag", "haul", "Source", "Cluster:", "rise", "fall", "shrink", "drop", "double", "\ufb02uctuate", "dwindle", "decline", "plunge", "decrease", "soar", "tumble", "surge", "spiral", "boom"], "regionBoundary": {"x2": 281.0, "y1": 257.67999267578125, "x1": 72.0, "y2": 360.67999267578125}, "caption": "Figure 2: Clustered verbs (source domains)", "page": 4}, {"figType": "Figure", "name": "1", "captionBoundary": {"x2": 257.0083312988281, "y1": 235.4211883544922, "x1": 103.91059875488281, "y2": 241.9910888671875}, "imageText": ["Source:", "MECHANISM", "Target", "Cluster:", "consensus", "relation", "tradition", "partnership", "resistance", "foundation", "alliance", "friendship", "contact", "reserve", "unity", "link", "peace", "bond", "myth", "identity", "hierarchy", "relation-", "ship", "connection", "balance", "marriage", "democracy", "defense", "faith", "empire", "distinction", "coalition", "regime", "division", "Source:", "STORY;", "JOURNEY", "Target", "Cluster:", "politics", "practice", "trading", "reading", "occupa-", "tion", "profession", "sport", "pursuit", "affair", "career", "thinking", "life", "Source:", "LOCATION;", "CONTAINER", "Target", "Cluster:", "lifetime", "quarter", "period", "century", "succes-", "sion", "stage", "generation", "decade", "phase", "interval", "future", "Source:", "LIVING", "BEING;", "END", "Target", "Cluster:", "defeat", "fall", "death", "tragedy", "loss", "collapse", "de-", "cline", "disaster", "destruction", "fate"], "regionBoundary": {"x2": 281.0, "y1": 70.67999267578125, "x1": 72.0, "y2": 223.67999267578125}, "caption": "Figure 1: Clustered target concepts", "page": 4}]}, "figures": [{"page_width": 0, "caption_boundary": {"x2": 356.95601569281683, "y1": 326.97387271457245, "x1": 144.32027604844833, "y2": 336.0987345377604}, "name": "1", "caption_text": "Figure 1: Clustered target concepts", "figure_type": "Figure", "uri": null, "page_height": 0, "figure_boundary": {"x2": 390.0, "y1": 98.0, "x1": 100.0, "y2": 311.0}, "page": 4, "dpi": 0}], "error": null, "pdf": "/work/host-output/3788297715225f81ec1ee2718be23e237384f375/C10-1113.pdf", "dpi": 100}