{"raw_detected_boxes": [[], [{"x2": 397.0, "y1": 87.0, "x1": 103.0, "y2": 208.0}, {"x2": 676.0, "y1": 615.0, "x1": 479.0, "y2": 711.0}], [{"x2": 406.0, "y1": 737.0, "x1": 100.0, "y2": 946.0}], [{"x2": 731.0, "y1": 443.0, "x1": 427.0, "y2": 502.0}, {"x2": 706.0, "y1": 880.0, "x1": 451.0, "y2": 957.0}], [{"x2": 333.0, "y1": 87.0, "x1": 170.0, "y2": 213.0}, {"x2": 729.0, "y1": 87.0, "x1": 419.0, "y2": 213.0}], [{"x2": 705.0, "y1": 87.0, "x1": 122.0, "y2": 244.0}, {"x2": 727.0, "y1": 412.0, "x1": 119.0, "y2": 683.0}], [{"x2": 721.0, "y1": 101.0, "x1": 103.0, "y2": 392.0}], [{"x2": 726.0, "y1": 106.0, "x1": 104.0, "y2": 416.0}, {"x2": 718.0, "y1": 595.0, "x1": 104.0, "y2": 925.0}], []], "raw_pdffigures_output": {"regionless-captions": [], "figures": [{"figType": "Figure", "name": "5", "captionBoundary": {"x2": 525.54638671875, "y1": 527.8671875, "x1": 72.00051879882812, "y2": 588.636962890625}, "imageText": ["1.", "0", "0.", "5", "0.", "0", "0.", "5", "0", "\u2212", "\u2212", "1.", "Labial\u2212Labial", "Coronal\u2212Coronal", "Dorsal\u2212Dorsal", "\u25cf", "\u25cf", "\u25cf", "\u25cf", "\u25cf", "\u25cf", "1.", "0", "0.", "5", "0.", "0", "0.", "5", "0", "\u2212", "\u2212", "1.", "Labial\u2212Labial", "Coronal\u2212Coronal", "Dorsal\u2212Dorsal", "\u25cf", "\u25cf", "\u25cf", "\u25cf", "\u25cf", "\u25cf", "\u25cf", "\u25cf", "\u25cf", "\u25cf", "\u25cf", "\u25cf", "\u25cf", "\u25cf\u25cf", "\u25cf", "\u25cf", "\u25cf", "\u25cf", "\u25cf", "\u25cf\u25cf", "\u25cf", "\u25cf", "\u25cf", "\u25cf", "\u25cf", "\u25cf\u25cf", "\u25cf", "\u25cf", "\u25cf", "\u25cf", "\u25cf", "\u25cf", "\u25cf", "\u25cf", "\u25cf", "\u25cf", "\u25cf", "\u25cf", "\u25cf", "\u25cf", "\u25cf", "\u25cf", "\u25cf", "\u25cf", "\u25cf", "\u25cf", "\u25cf", "\u25cf", "\u25cf", "\u25cf", "\u25cf", "\u25cf", "\u25cf", "\u25cf", "\u25cf", "\u25cf", "\u25cf", "\u25cf", "\u25cf"], "regionBoundary": {"x2": 523.0, "y1": 312.88970947265625, "x1": 87.75843048095703, "y2": 491.519287109375}, "caption": "Figure 5: Boxplots showing the distribution of association strength values (\u03c6) for self-successions of places of articulation. For the left boxplots about 3,200 languages were considered for which the Swadesh lists contained more than 20 successions. For the right boxplots only the top 99 languages were considered for which the Swadesh lists contained at least 100 successions, thereby removing most outliers and reducing the variance.", "page": 5}, {"figType": "Figure", "name": "3", "captionBoundary": {"x2": 525.5462646484375, "y1": 191.2552032470703, "x1": 72.00051879882812, "y2": 265.573974609375}, "imageText": ["K", "P", "T", "C"], "regionBoundary": {"x2": 509.0, "y1": 62.88970947265625, "x1": 87.0, "y2": 176.88970947265625}, "caption": "Figure 3: Successions of P, T, C and K in all languages. The \u201c+\u201d and \u201c\u2212\u201d signs indicate the polarity of a succession (going from row to column category). The color saturation of the background indicates the strength of association. In the left figure, places of articulation are sorted according to their position in the oral cavity, in the middle figure an automatic similarity sorting of matrix rows and columns was applied. The right part of the figure shows an alternative view only on those successions that have a positive association.", "page": 5}, {"figType": "Table", "name": "1", "captionBoundary": {"x2": 525.5457763671875, "y1": 530.5001220703125, "x1": 307.2764892578125, "y2": 659.015869140625}, "imageText": ["P", "T", "C", "K", "P", "\u221215", "+11", "+5", "\u22125", "T", "+12", "\u221210", "\u22125", "+13", "C", "+8", "\u22125", "\u22126", "+8", "K", "\u22123", "+8", "+5", "\u221215"], "regionBoundary": {"x2": 488.0, "y1": 441.88970947265625, "x1": 345.0, "y2": 512.8897094726562}, "caption": "Table 1: Results in Pozdniakov and Segerer (2007). The numbers indicate the overall sum of cells with negative vs. positive values with regard to successions of places of articulation (see Section 3 for a description of the labels P, T, C and K) for all languages in their sample. Positive and negative values have been assigned if the observed absolute value was at least 15% above (respectively below) the expected value. Compare their results with the left matrix in Figure 3.", "page": 1}, {"figType": "Figure", "name": "1", "captionBoundary": {"x2": 290.269775390625, "y1": 162.98719787597656, "x1": 72.00050354003906, "y2": 264.40496826171875}, "imageText": [], "regionBoundary": {"x2": 288.0, "y1": 61.88970947265625, "x1": 74.0, "y2": 150.88970947265625}, "caption": "Figure 1: Turkish vowel harmony patterns (left). The matrix visualizaton was generated on the basis of the Turkish Bible text and shows the palatal (front/back) and labial (rounding) harmony blocks. Rows and columns are automatically sorted according to the similarity of vowels. For non-harmonic languages, such as Spanish (right), no such patterns can be detected.", "page": 1}, {"figType": "Figure", "name": "6", "captionBoundary": {"x2": 525.5487060546875, "y1": 304.0992126464844, "x1": 72.00051879882812, "y2": 351.3189697265625}, "imageText": ["0", "0", "60", "0", "50", "0", "40", "0", "30", "0", "20", "0", "10", "\u22121.0", "\u22120.5", "0.0", "0.5", "1.0", "cy", "qu", "en", "F", "re", "Distribution", "of", "association", "values", "for", "all", "self\u2212successions", "across", "languages", "ue", "Labial,", "Coronal", "and", "Dorsal", "v", "al", "p", "hi", "ra", "ge", "A", "ve", "Number", "of", "consonant", "successions", "in", "dataset", "Average", "phi", "values", "in", "dependence", "of", "data", "amount", "0.", "4", "0.", "2", "0.", "0", "0.", "2", "4", "\u2212", "\u2212", "0.", "50", "100", "150", "200", "\u25cf", "\u25cf", "\u25cf", "\u25cf", "\u25cf", "\u25cf", "\u25cf", "\u25cf", "\u25cf", "\u25cf", "\u25cf", "\u25cf", "\u25cf", "\u25cf", "\u25cf", "\u25cf", "\u25cf", "\u25cf", "\u25cf", "\u25cf", "\u25cf", "\u25cf", "\u25cf", "\u25cf", "\u25cf", "\u25cf", "\u25cf", "\u25cf", "\u25cf", "\u25cf", "\u25cf", "\u25cf", "\u25cf", "\u25cf", "\u25cf", "\u25cf", "\u25cf", "\u25cf", "\u25cf", "\u25cf", "\u25cf", "\u25cf", "\u25cf", "\u25cf", "\u25cf", "\u25cf", "\u25cf\u25cf", "\u25cf", "\u25cf", "\u25cf", "\u25cf\u25cf", "\u25cf", "\u25cf", "\u25cf", "\u25cf", "\u25cf", "\u25cf\u25cf", "\u25cf", "\u25cf", "\u25cf", "\u25cf", "\u25cf", "\u25cf", "\u25cf", "\u25cf", "\u25cf", "\u25cf", "\u25cf\u25cf", "\u25cf", "\u25cf", "\u25cf", "\u25cf", "\u25cf", "\u25cf", "\u25cf", "\u25cf", "\u25cf", "\u25cf", "\u25cf", "\u25cf", "\u25cf", "\u25cf", "\u25cf", "\u25cf", "\u25cf", "\u25cf", "\u25cf", "\u25cf", "\u25cf", "\u25cf", "\u25cf", "\u25cf", "\u25cf", "\u25cf", "\u25cf", "\u25cf", "\u25cf", "\u25cf", "\u25cf", "\u25cf", "\u25cf", "\u25cf", "\u25cf", "\u25cf", "\u25cf", "\u25cf", "\u25cf", "\u25cf", "\u25cf", "\u25cf", "\u25cf", "\u25cf", "\u25cf", "\u25cf", "\u25cf", "\u25cf", "\u25cf", "\u25cf", "\u25cf", "\u25cf", "\u25cf", "\u25cf", "\u25cf", "\u25cf", "\u25cf", "\u25cf", "\u25cf", "\u25cf", "\u25cf", "\u25cf", "\u25cf", "\u25cf", "\u25cf", "\u25cf", "\u25cf", "\u25cf", "\u25cf", "\u25cf", "\u25cf", "\u25cf", "\u25cf", "\u25cf", "\u25cf", "\u25cf", "\u25cf", "\u25cf", "\u25cf", "\u25cf", "\u25cf", "\u25cf", "\u25cf", "\u25cf", "\u25cf", "\u25cf", "\u25cf", "\u25cf", "\u25cf", "\u25cf", "\u25cf", "\u25cf", "\u25cf", "\u25cf", "\u25cf", "\u25cf", "\u25cf", "\u25cf", "\u25cf", "\u25cf", "\u25cf", "\u25cf", "\u25cf", "\u25cf", "\u25cf", "\u25cf", "\u25cf", "\u25cf\u25cf", "\u25cf", "\u25cf", "\u25cf", "\u25cf", "\u25cf", "\u25cf", "\u25cf", "\u25cf", "\u25cf", "\u25cf", "\u25cf", "\u25cf", "\u25cf", "\u25cf", "\u25cf", "\u25cf", "\u25cf", "\u25cf", "\u25cf", "\u25cf", "\u25cf", "\u25cf", "\u25cf", "\u25cf", "\u25cf", "\u25cf", "\u25cf", "\u25cf", "\u25cf", "\u25cf", "\u25cf", "\u25cf", "\u25cf\u25cf", "\u25cf", "\u25cf", "\u25cf", "\u25cf", "\u25cf", "\u25cf", "\u25cf", "\u25cf", "\u25cf", "\u25cf", "\u25cf", "\u25cf", "\u25cf", "\u25cf", "\u25cf", "\u25cf", "\u25cf\u25cf\u25cf", "\u25cf", "\u25cf", "\u25cf\u25cf", "\u25cf", "\u25cf", "\u25cf", "\u25cf", "\u25cf", "\u25cf", "\u25cf", "\u25cf", "\u25cf", "\u25cf", "\u25cf", "\u25cf", "\u25cf", "\u25cf", "\u25cf", "\u25cf", "\u25cf", "\u25cf", "\u25cf", "\u25cf", "\u25cf", "\u25cf", "\u25cf", "\u25cf", "\u25cf", "\u25cf", "\u25cf", "\u25cf", "\u25cf", "\u25cf", "\u25cf", "\u25cf", "\u25cf", "\u25cf", "\u25cf", "\u25cf", "\u25cf", "\u25cf", "\u25cf", "\u25cf", "\u25cf", "\u25cf", "\u25cf", "\u25cf", "\u25cf", "\u25cf\u25cf", "\u25cf", "\u25cf", "\u25cf", "\u25cf", "\u25cf", "\u25cf", "\u25cf", "\u25cf", "\u25cf", "\u25cf", "\u25cf", "\u25cf", "\u25cf", "\u25cf", "\u25cf", "\u25cf\u25cf", "\u25cf", "\u25cf", "\u25cf", "\u25cf", "\u25cf", "\u25cf", "\u25cf", "\u25cf", "\u25cf", "\u25cf", "\u25cf", "\u25cf", "\u25cf", "\u25cf", "\u25cf", "\u25cf", "\u25cf\u25cf", "\u25cf", "\u25cf", "\u25cf", "\u25cf", "\u25cf", "\u25cf", "\u25cf", "\u25cf", "\u25cf", "\u25cf", "\u25cf", "\u25cf", "\u25cf", "\u25cf", "\u25cf", "\u25cf", "\u25cf", "\u25cf", "\u25cf", "\u25cf", "\u25cf", "\u25cf", "\u25cf", "\u25cf", "\u25cf", "\u25cf", "\u25cf", "\u25cf", "\u25cf", "\u25cf", "\u25cf", "\u25cf", "\u25cf", "\u25cf", "\u25cf", "\u25cf", "\u25cf", "\u25cf", "\u25cf", "\u25cf", "\u25cf", "\u25cf", "\u25cf", "\u25cf", "\u25cf\u25cf", "\u25cf", "\u25cf", "\u25cf", "\u25cf", "\u25cf", "\u25cf", "\u25cf", "\u25cf", "\u25cf", "\u25cf", "\u25cf", "\u25cf", "\u25cf", "\u25cf", "\u25cf", "\u25cf", "\u25cf", "\u25cf", "\u25cf", "\u25cf", "\u25cf", "\u25cf", "\u25cf", "\u25cf", "\u25cf", "\u25cf", "\u25cf", "\u25cf", "\u25cf", "\u25cf", "\u25cf", "\u25cf", "\u25cf", "\u25cf", "\u25cf", "\u25cf", "\u25cf", "\u25cf", "\u25cf", "\u25cf", "\u25cf", "\u25cf", "\u25cf", "\u25cf", "\u25cf", "\u25cf", "\u25cf", "\u25cf", "\u25cf", "\u25cf\u25cf", "\u25cf", "\u25cf", "\u25cf", "\u25cf", "\u25cf", "\u25cf\u25cf", "\u25cf", "\u25cf", "\u25cf", "\u25cf", "\u25cf", "\u25cf", "\u25cf", "\u25cf", "\u25cf", "\u25cf", "\u25cf", "\u25cf", "\u25cf", "\u25cf", "\u25cf", "\u25cf", "\u25cf", "\u25cf\u25cf", "\u25cf", "\u25cf", "\u25cf", "\u25cf", "\u25cf", "\u25cf", "\u25cf", "\u25cf", "\u25cf", "\u25cf", "\u25cf", "\u25cf", "\u25cf", "\u25cf", "\u25cf", "\u25cf", "\u25cf", "\u25cf", "\u25cf", "\u25cf", "\u25cf", "\u25cf", "\u25cf", "\u25cf", "\u25cf", "\u25cf", "\u25cf", "\u25cf", "\u25cf", "\u25cf", "\u25cf", "\u25cf", "\u25cf", "\u25cf", "\u25cf", "\u25cf", "\u25cf", "\u25cf", "\u25cf", "\u25cf", "\u25cf", "\u25cf", "\u25cf", "\u25cf", "\u25cf", "\u25cf", "\u25cf", "\u25cf", "\u25cf", "\u25cf", "\u25cf", "\u25cf", "\u25cf", "\u25cf", "\u25cf", "\u25cf", "\u25cf", "\u25cf", "\u25cf", "\u25cf", "\u25cf", "\u25cf", "\u25cf", "\u25cf", "\u25cf", "\u25cf", "\u25cf", "\u25cf", "\u25cf", "\u25cf", "\u25cf", "\u25cf", "\u25cf", "\u25cf", "\u25cf", "\u25cf", "\u25cf", "\u25cf", "\u25cf", "\u25cf", "\u25cf", "\u25cf", "\u25cf", "\u25cf", "\u25cf", "\u25cf", "\u25cf", "\u25cf", "\u25cf", "\u25cf", "\u25cf", "\u25cf", "\u25cf", "\u25cf", "\u25cf", "\u25cf", "\u25cf", "\u25cf", "\u25cf", "\u25cf", "\u25cf", "\u25cf", "\u25cf", "\u25cf", "\u25cf", "\u25cf", "\u25cf", "\u25cf", "\u25cf", "\u25cf", "\u25cf", "\u25cf", "\u25cf", "\u25cf", "\u25cf", "\u25cf", "\u25cf", "\u25cf", "\u25cf", "\u25cf", "\u25cf", "\u25cf", "\u25cf", "\u25cf", "\u25cf", "\u25cf", "\u25cf", "\u25cf", "\u25cf", "\u25cf", "\u25cf", "\u25cf", "\u25cf", "\u25cf", "\u25cf", "\u25cf", "\u25cf", "\u25cf", "\u25cf", "\u25cf", "\u25cf", "\u25cf", "\u25cf", "\u25cf", "\u25cf", "\u25cf", "\u25cf", "\u25cf", "\u25cf\u25cf", "\u25cf\u25cf", "\u25cf", "\u25cf", "\u25cf", "\u25cf", "\u25cf", "\u25cf", "\u25cf", "\u25cf", "\u25cf", "\u25cf", "\u25cf", "\u25cf", "\u25cf", "\u25cf", "\u25cf", "\u25cf", "\u25cf", "\u25cf", "\u25cf", "\u25cf", "\u25cf", "\u25cf", "\u25cf", "\u25cf", "\u25cf", "\u25cf", "\u25cf", "\u25cf", "\u25cf", "\u25cf", "\u25cf", "\u25cf", "\u25cf", "\u25cf", "\u25cf\u25cf", "\u25cf", "\u25cf\u25cf", "\u25cf", "\u25cf", "\u25cf", "\u25cf\u25cf", "\u25cf", "\u25cf", "\u25cf", "\u25cf", "\u25cf", "\u25cf", "\u25cf", "\u25cf", "\u25cf", "\u25cf", "\u25cf", "\u25cf", "\u25cf", "\u25cf", "\u25cf", "\u25cf", "\u25cf", "\u25cf", "\u25cf", "\u25cf", "\u25cf", "\u25cf", "\u25cf", "\u25cf", "\u25cf", "\u25cf", "\u25cf", "\u25cf", "\u25cf", "\u25cf", "\u25cf", "\u25cf", "\u25cf", "\u25cf", "\u25cf", "\u25cf", "\u25cf", "\u25cf", "\u25cf", "\u25cf", "\u25cf", "\u25cf", "\u25cf", "\u25cf", "\u25cf", "\u25cf", "\u25cf", "\u25cf", "\u25cf", "\u25cf", "\u25cf", "\u25cf", "\u25cf", "\u25cf", "\u25cf", "\u25cf", "\u25cf", "\u25cf", "\u25cf", "\u25cf", "\u25cf", "\u25cf", "\u25cf", "\u25cf", "\u25cf", "\u25cf", "\u25cf", "\u25cf", "\u25cf", "\u25cf", "\u25cf", "\u25cf", "\u25cf", "\u25cf", "\u25cf", "\u25cf", "\u25cf", "\u25cf", "\u25cf", "\u25cf", "\u25cf", "\u25cf", "\u25cf", "\u25cf", "\u25cf", "\u25cf", "\u25cf", "\u25cf", "\u25cf", "\u25cf", "\u25cf", "\u25cf", "\u25cf", "\u25cf", "\u25cf", "\u25cf", "\u25cf", "\u25cf", "\u25cf", "\u25cf", "\u25cf", "\u25cf", "\u25cf", "\u25cf", "\u25cf", "\u25cf", "\u25cf", "\u25cf", "\u25cf", "\u25cf", "\u25cf", "\u25cf", "\u25cf", "\u25cf", "\u25cf", "\u25cf", "\u25cf", "\u25cf", "\u25cf", "\u25cf", "\u25cf", "\u25cf", "\u25cf", "\u25cf\u25cf", "\u25cf", "\u25cf", "\u25cf", "\u25cf", "\u25cf", "\u25cf", "\u25cf", "\u25cf", "\u25cf", "\u25cf", "\u25cf", "\u25cf", "\u25cf", "\u25cf", "\u25cf", "\u25cf", "\u25cf", "\u25cf", "\u25cf", "\u25cf", "\u25cf", "\u25cf", "\u25cf", "\u25cf", "\u25cf", "\u25cf", "\u25cf", "\u25cf", "\u25cf", "\u25cf", "\u25cf", "\u25cf", "\u25cf", "\u25cf", "\u25cf", "\u25cf", "\u25cf", "\u25cf", "\u25cf", "\u25cf", "\u25cf", "\u25cf", "\u25cf", "\u25cf", "\u25cf", "\u25cf", "\u25cf", "\u25cf", "\u25cf", "\u25cf", "\u25cf", "\u25cf", "\u25cf", "\u25cf", "\u25cf", "\u25cf", "\u25cf", "\u25cf", "\u25cf", "\u25cf", "\u25cf", "\u25cf", "\u25cf", "\u25cf", "\u25cf", "\u25cf", "\u25cf", "\u25cf", "\u25cf", "\u25cf", "\u25cf", "\u25cf", "\u25cf", "\u25cf", "\u25cf", "\u25cf", "\u25cf", "\u25cf", "\u25cf", "\u25cf", "\u25cf", "\u25cf", "\u25cf", "\u25cf", "\u25cf", "\u25cf", "\u25cf", "\u25cf", "\u25cf", "\u25cf", "\u25cf", "\u25cf\u25cf", "\u25cf", "\u25cf", "\u25cf", "\u25cf", "\u25cf", "\u25cf\u25cf", "\u25cf", "\u25cf", "\u25cf", "\u25cf", "\u25cf", "\u25cf", "\u25cf", "\u25cf", "\u25cf", "\u25cf", "\u25cf", "\u25cf", "\u25cf", "\u25cf", "\u25cf", "\u25cf", "\u25cf", "\u25cf", "\u25cf", "\u25cf", "\u25cf", "\u25cf", "\u25cf", "\u25cf\u25cf", "\u25cf", "\u25cf", "\u25cf", "\u25cf", "\u25cf", "\u25cf", "\u25cf", "\u25cf", "\u25cf", "\u25cf", "\u25cf", "\u25cf", "\u25cf", "\u25cf", "\u25cf", "\u25cf", "\u25cf\u25cf", "\u25cf", "\u25cf", "\u25cf", "\u25cf", "\u25cf", "\u25cf", "\u25cf", "\u25cf", "\u25cf", "\u25cf", "\u25cf", "\u25cf", "\u25cf", "\u25cf", "\u25cf", "\u25cf", "\u25cf", "\u25cf", "\u25cf", "\u25cf", "\u25cf", "\u25cf", "\u25cf", "\u25cf", "\u25cf", "\u25cf", "\u25cf", "\u25cf", "\u25cf", "\u25cf", "\u25cf", "\u25cf", "\u25cf", "\u25cf", "\u25cf\u25cf", "\u25cf", "\u25cf", "\u25cf", "\u25cf", "\u25cf", "\u25cf", "\u25cf", "\u25cf", "\u25cf", "\u25cf", "\u25cf", "\u25cf", "\u25cf", "\u25cf", "\u25cf", "\u25cf", "\u25cf", "\u25cf", "\u25cf", "\u25cf\u25cf", "\u25cf", "\u25cf", "\u25cf", "\u25cf", "\u25cf", "\u25cf", "\u25cf", "\u25cf", "\u25cf", "\u25cf", "\u25cf", "\u25cf\u25cf", "\u25cf", "\u25cf", "\u25cf", "\u25cf", "\u25cf", "\u25cf", "\u25cf", "\u25cf", "\u25cf", "\u25cf", "\u25cf", "\u25cf", "\u25cf", "\u25cf", "\u25cf", "\u25cf", "\u25cf", "\u25cf", "\u25cf", "\u25cf\u25cf", "\u25cf", "\u25cf", "\u25cf", "\u25cf", "\u25cf", "\u25cf", "\u25cf", "\u25cf", "\u25cf", "\u25cf", "\u25cf", "\u25cf", "\u25cf", "\u25cf", "\u25cf", "\u25cf", "\u25cf\u25cf", "\u25cf", "\u25cf\u25cf", "\u25cf", "\u25cf", "\u25cf", "\u25cf", "\u25cf", "\u25cf", "\u25cf", "\u25cf", "\u25cf", "\u25cf", "\u25cf", "\u25cf", "\u25cf", "\u25cf", "\u25cf", "\u25cf"], "regionBoundary": {"x2": 520.8411865234375, "y1": 74.4922103881836, "x1": 75.93585205078125, "y2": 280.7088623046875}, "caption": "Figure 6: The scatter plot on the left displays the average \u03c6 values for self-successions of all places of articulation depending on the number of consonant successions (CVC) for each language in the sample. The histogram on the right shows the distribution of association strength values (\u03c6) for self-successions of places of articulation in more than 3200 languages.", "page": 6}, {"figType": "Table", "name": "2", "captionBoundary": {"x2": 290.2696838378906, "y1": 693.7831420898438, "x1": 72.00050354003906, "y2": 713.9049072265625}, "imageText": ["D", "K", "5,", "k,", "g,", "x,", "N,", "q,", "G,", "X,", "7,", "h", "\u00f1,", "k,", "g,", "x,", "G,", "N,", "q,", "G,", "X,", "K,", "\u00e8,", "Q,", "P,", "h,", "H,", "C", "C,", "j,", "T,", "l,", "L,", "r,", "y", "\u00d9,", "\u00c3,", "c,", "\u00e9,", "l,", "L,", "\u00ed,", "L,", "r,", "R,", "j", "z,", "ts,", "dz,", "n,", "S,", "Z", "8,", "4,", "t,", "d,", "s,", "z,", "c,", "n,", "S,", "Z", "T,", "D,", "n", "\u02c6", ",", "t,", "d,", "s,", "C", "T", "f,", "v,", "w", "LCD", "PTCK", "ASJP", "IPA", "L", "P", "p,", "b,", "m,", "f,", "v,", "w", "p,", "F,", "b,", "B,", "m,"], "regionBoundary": {"x2": 294.0, "y1": 529.8897094726562, "x1": 72.0, "y2": 680.8897094726562}, "caption": "Table 2: Assignment of consonants to symbols. All varieties of \u201cclick\u201d-sounds have been ignored.", "page": 2}, {"figType": "Figure", "name": "8", "captionBoundary": {"x2": 525.5463256835938, "y1": 681.8121337890625, "x1": 72.00050354003906, "y2": 742.5819091796875}, "imageText": [], "regionBoundary": {"x2": 518.0, "y1": 402.88970947265625, "x1": 70.0, "y2": 666.8897094726562}, "caption": "Figure 8: Density equalized distribution of the languages with respect to SPA. The area of the geographic regions corresponds to the number of languages in that location \u2013 represented by dots. Overlap is avoided using pixel-placement. The color mapping corresponds to the one used in the WALS map (Figure 7). Locations of nonconforming languages are highlighted with red boxes. Note that the number of languages in this map is about twice the number in the WALS map (7).", "page": 7}, {"figType": "Figure", "name": "7", "captionBoundary": {"x2": 525.5496826171875, "y1": 316.8791809082031, "x1": 72.00050354003906, "y2": 364.09893798828125}, "imageText": [], "regionBoundary": {"x2": 526.0, "y1": 74.88970947265625, "x1": 69.0, "y2": 302.88970947265625}, "caption": "Figure 7: WALS map of the languages and their behavior with respect to SPA. The color indicates the number of self-succession \u03c6 values which are negative, i.e., which adhere to the SPA principle. Color mapping is from blue (conforming to SPA) to red. The numbers in square brackets indicate the number of languages in this group.", "page": 7}, {"figType": "Table", "name": "4", "captionBoundary": {"x2": 522.5769653320312, "y1": 701.7871704101562, "x1": 310.2444763183594, "y2": 708.3599243164062}, "imageText": ["labial", "coronal", "dorsal", "labial", "\u22120.360", "+0.187", "+0.183", "coronal", "+0.259", "\u22120.243", "\u22120.068", "dorsal", "\u22120.010", "+0.097", "\u22120.121"], "regionBoundary": {"x2": 508.0, "y1": 632.8897094726562, "x1": 325.0, "y2": 688.8897094726562}, "caption": "Table 4: Matrix of \u03c6 values for Egyptian Arabic.", "page": 3}, {"figType": "Table", "name": "3", "captionBoundary": {"x2": 525.5454711914062, "y1": 373.8341979980469, "x1": 307.2764892578125, "y2": 395.5928955078125}, "imageText": ["P2", "\u00acP2", "P1", "A", ":", "n(P1", "\u2192", "P2)", "B:", "n(P1", "\u2192", "\u00acP2)", "\u00acP1", "C", ":", "n(\u00acP1", "\u2192", "P2)", "D", ":", "n(\u00acP1", "\u2192", "\u00acP2)"], "regionBoundary": {"x2": 533.0, "y1": 318.88970947265625, "x1": 307.0, "y2": 360.88970947265625}, "caption": "Table 3: Contingency table for the articulation place (P) succession from P1 to P2.", "page": 3}, {"figType": "Figure", "name": "4", "captionBoundary": {"x2": 525.5482177734375, "y1": 168.6361846923828, "x1": 307.2765197753906, "y2": 256.50396728515625}, "imageText": [], "regionBoundary": {"x2": 525.0, "y1": 62.88970947265625, "x1": 300.0, "y2": 153.88970947265625}, "caption": "Figure 4: The \u03c6 matrix considering only the three main categories for all the data across languages. In the left figure, the categories are sorted according to their position in the oral cavity. In the right figure, the categories are sorted automatically, which shows that D and L are more similar to each other than D and C.", "page": 4}, {"figType": "Figure", "name": "2", "captionBoundary": {"x2": 290.2734680175781, "y1": 168.70118713378906, "x1": 72.00051879882812, "y2": 229.470947265625}, "imageText": [], "regionBoundary": {"x2": 243.0, "y1": 62.88970947265625, "x1": 120.0, "y2": 153.88970947265625}, "caption": "Figure 2: Visualization of the \u03c6 matrix from Table 4 (Egyptian Arabic), L stands for labial, C for coronal and D for dorsal. It can be seen that all diagonal values (successions of the same place of articulation) have negative associations (red color).", "page": 4}]}, "figures": [{"page_width": 0, "caption_boundary": {"x2": 403.1524658203125, "y1": 226.37110816107855, "x1": 100.00069936116536, "y2": 367.22912258572046}, "name": "1", "caption_text": "Figure 1: Turkish vowel harmony patterns (left). The matrix visualizaton was generated on the basis of the Turkish Bible text and shows the palatal (front/back) and labial (rounding) harmony blocks. Rows and columns are automatically sorted according to the similarity of vowels. For non-harmonic languages, such as Spanish (right), no such patterns can be detected.", "figure_type": "Figure", "uri": null, "page_height": 0, "figure_boundary": {"x2": 400.0, "y1": 87.0, "x1": 103.0, "y2": 225.0}, "page": 1, "dpi": 0}, {"page_width": 0, "caption_boundary": {"x2": 729.9246893988715, "y1": 736.8057250976562, "x1": 426.7729017469618, "y2": 915.299818250868}, "name": "1", "caption_text": "Table 1: Results in Pozdniakov and Segerer (2007). The numbers indicate the overall sum of cells with negative vs. positive values with regard to successions of places of articulation (see Section 3 for a description of the labels P, T, C and K) for all languages in their sample. Positive and negative values have been assigned if the observed absolute value was at least 15% above (respectively below) the expected value. Compare their results with the left matrix in Figure 3.", "figure_type": "Table", "uri": null, "page_height": 0, "figure_boundary": {"x2": 678.0, "y1": 614.0, "x1": 479.0, "y2": 712.0}, "page": 1, "dpi": 0}, {"page_width": 0, "caption_boundary": {"x2": 403.15233866373694, "y1": 963.5876973470051, "x1": 100.00069936116536, "y2": 991.5345933702257}, "name": "2", "caption_text": "Table 2: Assignment of consonants to symbols. All varieties of \u201cclick\u201d-sounds have been ignored.", "figure_type": "Table", "uri": null, "page_height": 0, "figure_boundary": {"x2": 408.0, "y1": 735.0, "x1": 100.0, "y2": 963.0}, "page": 2, "dpi": 0}, {"page_width": 0, "caption_boundary": {"x2": 729.9242655436198, "y1": 519.2141638861762, "x1": 426.7729017469618, "y2": 549.434577094184}, "name": "3", "caption_text": "Table 3: Contingency table for the articulation place (P) succession from P1 to P2.", "figure_type": "Table", "uri": null, "page_height": 0, "figure_boundary": {"x2": 739.0, "y1": 442.0, "x1": 426.0, "y2": 519.0}, "page": 3, "dpi": 0}, {"page_width": 0, "caption_boundary": {"x2": 725.8013407389323, "y1": 974.7044033474392, "x1": 430.8951059977213, "y2": 983.8332282172308}, "name": "4", "caption_text": "Table 4: Matrix of \u03c6 values for Egyptian Arabic.", "figure_type": "Table", "uri": null, "page_height": 0, "figure_boundary": {"x2": 714.0, "y1": 878.0, "x1": 447.0, "y2": 974.0}, "page": 3, "dpi": 0}, {"page_width": 0, "caption_boundary": {"x2": 403.1575944688585, "y1": 234.3072043524848, "x1": 100.00072055392795, "y2": 318.70964898003473}, "name": "2", "caption_text": "Figure 2: Visualization of the \u03c6 matrix from Table 4 (Egyptian Arabic), L stands for labial, C for coronal and D for dorsal. It can be seen that all diagonal values (successions of the same place of articulation) have negative associations (red color).", "figure_type": "Figure", "uri": null, "page_height": 0, "figure_boundary": {"x2": 336.0, "y1": 87.0, "x1": 167.0, "y2": 213.0}, "page": 4, "dpi": 0}, {"page_width": 0, "caption_boundary": {"x2": 729.9280802408854, "y1": 234.21692318386502, "x1": 426.77294413248694, "y2": 356.2555101182726}, "name": "4", "caption_text": "Figure 4: The \u03c6 matrix considering only the three main categories for all the data across languages. In the left figure, the categories are sorted according to their position in the oral cavity. In the right figure, the categories are sorted automatically, which shows that D and L are more similar to each other than D and C.", "figure_type": "Figure", "uri": null, "page_height": 0, "figure_boundary": {"x2": 729.0, "y1": 87.0, "x1": 417.0, "y2": 213.0}, "page": 4, "dpi": 0}, {"page_width": 0, "caption_boundary": {"x2": 729.9253675672743, "y1": 265.6322267320421, "x1": 100.00072055392795, "y2": 368.8527425130208}, "name": "3", "caption_text": "Figure 3: Successions of P, T, C and K in all languages. The \u201c+\u201d and \u201c\u2212\u201d signs indicate the polarity of a succession (going from row to column category). The color saturation of the background indicates the strength of association. In the left figure, places of articulation are sorted according to their position in the oral cavity, in the middle figure an automatic similarity sorting of matrix rows and columns was applied. The right part of the figure shows an alternative view only on those successions that have a positive association.", "figure_type": "Figure", "uri": null, "page_height": 0, "figure_boundary": {"x2": 708.0, "y1": 87.0, "x1": 121.0, "y2": 244.0}, "page": 5, "dpi": 0}, {"page_width": 0, "caption_boundary": {"x2": 729.925537109375, "y1": 733.1488715277777, "x1": 100.00072055392795, "y2": 817.5513373480902}, "name": "5", "caption_text": "Figure 5: Boxplots showing the distribution of association strength values (\u03c6) for self-successions of places of articulation. For the left boxplots about 3,200 languages were considered for which the Swadesh lists contained more than 20 successions. For the right boxplots only the top 99 languages were considered for which the Swadesh lists contained at least 100 successions, thereby removing most outliers and reducing the variance.", "figure_type": "Figure", "uri": null, "page_height": 0, "figure_boundary": {"x2": 727.0, "y1": 412.0, "x1": 119.0, "y2": 683.0}, "page": 5, "dpi": 0}, {"page_width": 0, "caption_boundary": {"x2": 729.9287584092882, "y1": 422.36001756456164, "x1": 100.00072055392795, "y2": 487.94301350911456}, "name": "6", "caption_text": "Figure 6: The scatter plot on the left displays the average \u03c6 values for self-successions of all places of articulation depending on the number of consonant successions (CVC) for each language in the sample. The histogram on the right shows the distribution of association strength values (\u03c6) for self-successions of places of articulation in more than 3200 languages.", "figure_type": "Figure", "uri": null, "page_height": 0, "figure_boundary": {"x2": 723.0, "y1": 101.0, "x1": 102.0, "y2": 392.0}, "page": 6, "dpi": 0}, {"page_width": 0, "caption_boundary": {"x2": 729.9301147460938, "y1": 440.1099734836154, "x1": 100.00069936116536, "y2": 505.6929694281684}, "name": "7", "caption_text": "Figure 7: WALS map of the languages and their behavior with respect to SPA. The color indicates the number of self-succession \u03c6 values which are negative, i.e., which adhere to the SPA principle. Color mapping is from blue (conforming to SPA) to red. The numbers in square brackets indicate the number of languages in this group.", "figure_type": "Figure", "uri": null, "page_height": 0, "figure_boundary": {"x2": 730.0, "y1": 104.0, "x1": 98.0, "y2": 419.0}, "page": 7, "dpi": 0}, {"page_width": 0, "caption_boundary": {"x2": 729.9254523383246, "y1": 946.9612969292534, "x1": 100.00069936116536, "y2": 1031.363762749566}, "name": "8", "caption_text": "Figure 8: Density equalized distribution of the languages with respect to SPA. The area of the geographic regions corresponds to the number of languages in that location \u2013 represented by dots. Overlap is avoided using pixel-placement. The color mapping corresponds to the one used in the WALS map (Figure 7). Locations of nonconforming languages are highlighted with red boxes. Note that the number of languages in this map is about twice the number in the WALS map (7).", "figure_type": "Figure", "uri": null, "page_height": 0, "figure_boundary": {"x2": 718.0, "y1": 592.0, "x1": 98.0, "y2": 925.0}, "page": 7, "dpi": 0}], "error": null, "pdf": "/work/host-output/9b31836bb2e6e716746c5aeb7ac91099a97e5059/W10-2110.pdf", "dpi": 100}