{"raw_detected_boxes": [[], [], [{"x2": 629.0, "y1": 143.0, "x1": 204.0, "y2": 387.0}], [{"x2": 708.0, "y1": 879.0, "x1": 115.0, "y2": 957.0}], [{"x2": 744.0, "y1": 97.0, "x1": 107.0, "y2": 346.0}, {"x2": 729.0, "y1": 522.0, "x1": 101.0, "y2": 1003.0}], [{"x2": 729.0, "y1": 87.0, "x1": 108.0, "y2": 308.0}], [{"x2": 630.0, "y1": 326.0, "x1": 199.0, "y2": 401.0}, {"x2": 611.0, "y1": 469.0, "x1": 219.0, "y2": 646.0}], [{"x2": 726.0, "y1": 88.0, "x1": 104.0, "y2": 529.0}], []], "raw_pdffigures_output": {"regionless-captions": [{"figType": "Figure", "boundary": {"x2": 381.67144775390625, "y1": 394.913330078125, "x1": 215.875, "y2": 401.4860534667969}, "text": "Figure 7: C Open Confusion Matrices", "name": "7", "page": 7}], "figures": [{"figType": "Figure", "name": "5", "captionBoundary": {"x2": 371.2206115722656, "y1": 219.70826721191406, "x1": 226.3260040283203, "y2": 226.281005859375}, "imageText": ["(c)", "2-stage", "80", "60", "40", "20", "0", "d", "G", "ol", "hr", "bs", "sr", "pt-BR", "pt-PT", "Predicted", "T", "pt", "-P", "R", "pt", "-B", "hr", "bs", "s", "r", "(b)", "NN", "80", "60", "40", "20", "0", "d", "G", "ol", "hr", "bs", "sr", "pt-BR", "pt-PT", "Predicted", "T", "pt", "-P", "R", "pt", "-B", "hr", "bs", "s", "r", "(a)", "LR", "80", "60", "40", "20", "0", "bs", "hr", "G", "ol", "d", "sr", "pt-BR", "pt-PT", "pt", "-P", "T", "Predicted", "R", "pt", "-B", "hr", "bs", "s", "r"], "regionBoundary": {"x2": 524.802978515625, "y1": 62.8900146484375, "x1": 75.73308563232422, "y2": 203.84503173828125}, "caption": "Figure 5: B2 Confusion Matrices", "page": 5}, {"figType": "Table", "name": "4", "captionBoundary": {"x2": 370.7897644042969, "y1": 479.0562744140625, "x1": 226.7570037841797, "y2": 485.6289978027344}, "imageText": ["OPEN", "LR", "44", "33", "43", "55", "48", "NN", "52", "35", "48", "61", "49", "EMV", "52", "35", "48", "61", "50", "CLOSED", "LR", "45", "33", "43", "54", "48", "NN", "52", "35", "48", "61", "49", "EMV", "52", "34", "48", "61", "50", "XXXXXXXXXXXMethod", "Dialect", "EGY", "GLF", "LAV", "MSA", "NOR"], "regionBoundary": {"x2": 440.0, "y1": 335.3228759765625, "x1": 157.0, "y2": 466.8900146484375}, "caption": "Table 4: Task 2 dialects F1-score", "page": 6}, {"figType": "Table", "name": "3", "captionBoundary": {"x2": 441.8691711425781, "y1": 302.8783264160156, "x1": 155.6800079345703, "y2": 309.4510498046875}, "imageText": ["Accuracy", "44.42", "49.03", "49.03", "44.35", "49.03", "49.09", "F1-weighted", "44.79", "49.17", "49.22", "44.74", "49.17", "49.29", "PPPPPPPPMetric", "Data", "Closed", "Open", "LR", "NN", "EMV5", "LR", "NN", "EMV2"], "regionBoundary": {"x2": 454.0, "y1": 232.10394287109375, "x1": 143.0, "y2": 289.8900146484375}, "caption": "Table 3: Task 2 results. System ranks are indicated in superscript.", "page": 6}, {"figType": "Figure", "name": "1", "captionBoundary": {"x2": 388.8940124511719, "y1": 291.6333312988281, "x1": 208.6540069580078, "y2": 298.2060546875}, "imageText": [], "regionBoundary": {"x2": 454.0, "y1": 102.8900146484375, "x1": 146.0, "y2": 278.8900146484375}, "caption": "Figure 1: Two-stage coarse-fine classifier", "page": 2}, {"figType": "Figure", "name": "6", "captionBoundary": {"x2": 385.0097961425781, "y1": 217.51026916503906, "x1": 212.53700256347656, "y2": 224.0830078125}, "imageText": ["150", "120", "90", "60", "30", "d", "G", "ol", "EGY", "GLF", "LAV", "MSA", "NOR", "R", "N", "O", "A", "M", "S", "LA", "V", "G", "LF", "Y", "E", "G", "150", "120", "90", "60", "30", "d", "G", "ol", "EGY", "GLF", "LAV", "MSA", "NOR", "R", "N", "O", "A", "M", "S", "LA", "V", "G", "LF", "Y", "E", "G", "150", "120", "90", "60", "30", "d", "G", "ol", "EGY", "GLF", "LAV", "MSA", "NOR", "R", "N", "O", "A", "M", "S", "LA", "V", "G", "LF", "Y", "E", "G"], "regionBoundary": {"x2": 524.805419921875, "y1": 239.8900146484375, "x1": 75.72449493408203, "y2": 358.48736572265625}, "caption": "Figure 6: C Closed Confusion Matrices", "page": 7}, {"figType": "Table", "name": "1", "captionBoundary": {"x2": 441.8691711425781, "y1": 702.124267578125, "x1": 155.67999267578125, "y2": 708.697021484375}, "imageText": ["LR", "NN", "2-stage3", "LR1", "NN", "2-stage", "LR1", "NN", "2-stage", "Accuracy", "88.59", "85.02", "88.70", "92.00", "89.60", "91.20", "87.80", "86.00", "87.20", "F1-weighted", "88.60", "84.93", "88.70", "91.94", "89.45", "91.12", "87.73", "85.81", "87.13", "PPPPPPPPMetric", "Data", "A", "B1", "B2"], "regionBoundary": {"x2": 518.0, "y1": 631.3508911132812, "x1": 80.0, "y2": 689.8900146484375}, "caption": "Table 1: Task 1 results. System ranks are indicated in superscript.", "page": 3}, {"figType": "Figure", "name": "2", "captionBoundary": {"x2": 407.56976318359375, "y1": 266.9183044433594, "x1": 189.97698974609375, "y2": 273.49102783203125}, "imageText": [], "regionBoundary": {"x2": 520.0, "y1": 168.8900146484375, "x1": 77.0, "y2": 254.8900146484375}, "caption": "Figure 2: Example of out-of-domain dataset entry", "page": 3}, {"figType": "Table", "name": "2", "captionBoundary": {"x2": 377.8097839355469, "y1": 261.7832946777344, "x1": 219.73699951171875, "y2": 268.35601806640625}, "imageText": ["B2", "LR", "92", "85", "91", "-", "-", "-", "-", "-", "-", "-", "86", "84", "NN", "90", "80", "92", "-", "-", "-", "-", "-", "-", "-", "85", "82", "2-stage", "92", "84", "91", "-", "-", "-", "-", "-", "-", "-", "85", "83", "B1", "LR", "93", "86", "92", "-", "-", "-", "-", "-", "-", "-", "94", "94", "NN", "88", "82", "95", "-", "-", "-", "-", "-", "-", "92", "91", "2-stage", "93", "86", "92", "-", "-", "-", "-", "-", "-", "-", "93", "92", "A", "LR", "85", "77", "90", "85", "80", "77", "94", "93", "98", "98", "93", "93", "NN", "82", "75", "88", "79", "73", "63", "92", "91", "96", "96", "91", "91", "2-stage", "85", "77", "90", "85", "80", "78", "94", "93", "98", "98", "94", "93", "XXXXXXXXXXXMethod", "Variant", "hr", "bs", "sr", "es-ar", "es-es", "es-mx", "fr-ca", "fr-fr", "id", "my", "pt-br", "pt-pt"], "regionBoundary": {"x2": 537.0, "y1": 59.868900299072266, "x1": 72.0, "y2": 248.8900146484375}, "caption": "Table 2: Task 1 per-variant F1-score", "page": 4}, {"figType": "Figure", "name": "4", "captionBoundary": {"x2": 371.2206115722656, "y1": 735.9442749023438, "x1": 226.3260040283203, "y2": 742.5170288085938}, "imageText": ["(c)", "2-stage", "80", "60", "40", "20", "0", "d", "G", "ol", "hr", "bs", "sr", "pt-BR", "pt-PT", "Predicted", "T", "pt", "-P", "R", "pt", "-B", "hr", "bs", "s", "r", "(b)", "NN", "80", "60", "40", "20", "0", "d", "G", "ol", "hr", "bs", "sr", "pt-BR", "pt-PT", "Predicted", "T", "pt", "-P", "R", "pt", "-B", "hr", "bs", "s", "r", "(a)", "LR", "80", "60", "40", "20", "0", "d", "G", "ol", "hr", "bs", "sr", "pt-BR", "pt-PT", "Predicted", "T", "pt", "-P", "R", "pt", "-B", "hr", "bs", "s", "r"], "regionBoundary": {"x2": 524.802978515625, "y1": 578.8900146484375, "x1": 75.73309326171875, "y2": 720.0809936523438}, "caption": "Figure 4: B1 Confusion Matrices", "page": 4}, {"figType": "Figure", "name": "3", "captionBoundary": {"x2": 368.7930603027344, "y1": 531.2113037109375, "x1": 228.7530059814453, "y2": 537.7840576171875}, "imageText": ["(c)", "2-stage", "800", "600", "400", "200", "0", "d", "G", "ol", "sr", "bs", "hr", "es-MX", "es-ES", "es-AR", "fr-FR", "fr-CA", "my", "id", "pt-PT", "pt-BR", "es", "-A", "R", "es", "-E", "S", "es", "-M", "X", "fr-", "C", "A", "fr-", "FR", "i", "d", "m", "y", "pt", "-B", "R", "pt", "-P", "T", "Predicted", "hr", "bs", "s", "r", "(b)", "NN", "800", "600", "400", "200", "0", "d", "G", "ol", "sr", "bs", "hr", "es-MX", "es-ES", "es-AR", "fr-FR", "fr-CA", "my", "id", "pt-PT", "pt-BR", "Predicted", "es", "-A", "R", "es", "-E", "S", "es", "-M", "X", "fr-", "C", "A", "fr-", "FR", "i", "d", "m", "y", "pt", "-B", "R", "pt", "-P", "T", "hr", "bs", "s", "r", "(a)", "LR", "800", "600", "400", "200", "0", "d", "G", "ol", "sr", "bs", "hr", "es-MX", "es-ES", "es-AR", "fr-FR", "fr-CA", "my", "id", "pt-PT", "pt-BR", "Predicted", "es", "-A", "R", "es", "-E", "S", "es", "-M", "X", "fr-", "C", "A", "fr-", "FR", "i", "d", "m", "y", "pt", "-B", "R", "pt", "-P", "T", "hr", "bs", "s", "r"], "regionBoundary": {"x2": 524.8359985351562, "y1": 375.8900146484375, "x1": 75.57147216796875, "y2": 515.3480224609375}, "caption": "Figure 3: A Confusion Matrices", "page": 4}]}, "figures": [{"page_width": 0, "caption_boundary": {"x2": 540.1305728488499, "y1": 405.0462934705946, "x1": 289.79723188612195, "y2": 414.1750759548611}, "name": "1", "caption_text": "Figure 1: Two-stage coarse-fine classifier", "figure_type": "Figure", "uri": null, "page_height": 0, "figure_boundary": {"x2": 629.0, "y1": 143.0, "x1": 204.0, "y2": 404.0}, "page": 2, "dpi": 0}, {"page_width": 0, "caption_boundary": {"x2": 613.7071821424696, "y1": 975.172593858507, "x1": 216.22221204969617, "y2": 984.3014187282986}, "name": "1", "caption_text": "Table 1: Task 1 results. System ranks are indicated in superscript.", "figure_type": "Table", "uri": null, "page_height": 0, "figure_boundary": {"x2": 719.0, "y1": 862.0, "x1": 111.0, "y2": 974.0}, "page": 3, "dpi": 0}, {"page_width": 0, "caption_boundary": {"x2": 524.7358110215929, "y1": 363.58790927463104, "x1": 305.1902770996094, "y2": 372.7166917588976}, "name": "2", "caption_text": "Table 2: Task 1 per-variant F1-score", "figure_type": "Table", "uri": null, "page_height": 0, "figure_boundary": {"x2": 746.0, "y1": 86.0, "x1": 100.0, "y2": 363.0}, "page": 4, "dpi": 0}, {"page_width": 0, "caption_boundary": {"x2": 512.2125837537977, "y1": 737.793477376302, "x1": 317.7125083075629, "y2": 746.9223022460938}, "name": "3", "caption_text": "Figure 3: A Confusion Matrices", "figure_type": "Figure", "uri": null, "page_height": 0, "figure_boundary": {"x2": 729.0, "y1": 522.0, "x1": 100.0, "y2": 1003.0}, "page": 4, "dpi": 0}, {"page_width": 0, "caption_boundary": {"x2": 515.5841827392578, "y1": 305.1503711276584, "x1": 314.34167226155597, "y2": 314.2791748046875}, "name": "5", "caption_text": "Figure 5: B2 Confusion Matrices", "figure_type": "Figure", "uri": null, "page_height": 0, "figure_boundary": {"x2": 729.0, "y1": 87.0, "x1": 100.0, "y2": 318.0}, "page": 5, "dpi": 0}, {"page_width": 0, "caption_boundary": {"x2": 613.7071821424696, "y1": 420.6643422444661, "x1": 216.22223324245877, "y2": 429.7931247287326}, "name": "3", "caption_text": "Table 3: Task 2 results. System ranks are indicated in superscript.", "figure_type": "Table", "uri": null, "page_height": 0, "figure_boundary": {"x2": 631.0, "y1": 325.0, "x1": 199.0, "y2": 403.0}, "page": 6, "dpi": 0}, {"page_width": 0, "caption_boundary": {"x2": 514.9857838948568, "y1": 665.3559366861979, "x1": 314.9402830335829, "y2": 674.4847191704644}, "name": "4", "caption_text": "Table 4: Task 2 dialects F1-score", "figure_type": "Table", "uri": null, "page_height": 0, "figure_boundary": {"x2": 611.0, "y1": 469.0, "x1": 219.0, "y2": 648.0}, "page": 6, "dpi": 0}, {"page_width": 0, "caption_boundary": {"x2": 534.735827975803, "y1": 302.09759606255426, "x1": 295.19028133816187, "y2": 311.2263997395833}, "name": "6", "caption_text": "Figure 6: C Closed Confusion Matrices", "figure_type": "Figure", "uri": null, "page_height": 0, "figure_boundary": {"x2": 729.0, "y1": 87.0, "x1": 100.0, "y2": 529.0}, "page": 7, "dpi": 0}], "error": null, "pdf": "/work/host-output/c65cc4743fdd19b99236906678fd40942cb4379c/W16-4804.pdf", "dpi": 100}